ayomide_sdk/__init__.py
ayomide_sdk/api_resources/__init__.py
ayomide_sdk/api_resources/abstract.py
ayomide_sdk/api_resources/api_requester.py
ayomide_sdk/api_resources/constants.py
ayomide_sdk/api_resources/helpers.py
ayomide_sdk/rest/__init__.py
ayomide_sdk/rest/movie/__init__.py
ayomide_sdk/rest/quote/__init__.py
ayomide_sdk-0.0.8.dist-info/LICENSE
ayomide_sdk-0.0.8.dist-info/METADATA
ayomide_sdk-0.0.8.dist-info/WHEEL
ayomide_sdk-0.0.8.dist-info/top_level.txt
ayomide_sdk-0.0.8.dist-info/RECORD
