Metadata-Version: 2.1
Name: ayomide-sdk
Version: 0.0.8
Summary: This is a simple Python library to
Home-page: https://github.com/alsaheem/ayomide-sdk
Author: Ayomide Adebisi
Author-email: adebisiayomide07@gmail.com
Project-URL: Bug Tracker, https://github.com/alsaheem/ayomide-sdk/issues
Classifier: Programming Language :: Python :: 3
Classifier: License :: OSI Approved :: BSD License
Classifier: Operating System :: OS Independent
Requires-Python: >=3.8
License-File: LICENSE
Requires-Dist: requests (>=2.31.0)
